trivver/__init__.py
trivver/__main__.py
trivver/py.typed
trivver/trivver.1
trivver/trivver.py
trivver-2.2.3.dist-info/METADATA
trivver-2.2.3.dist-info/WHEEL
trivver-2.2.3.dist-info/entry_points.txt
trivver-2.2.3.dist-info/RECORD
